aioethereum/__init__.py
aioethereum/client.py
aioethereum/constants.py
aioethereum/errors.py
aioethereum/utils.py
aioethereum/management/__init__.py
aioethereum/management/admin.py
aioethereum/management/db.py
aioethereum/management/debug.py
aioethereum/management/eth.py
aioethereum/management/miner.py
aioethereum/management/net.py
aioethereum/management/personal.py
aioethereum/management/shh.py
aioethereum/management/txpool.py
aioethereum/management/web3.py
aioethereum-0.2.2.dist-info/DESCRIPTION.rst
aioethereum-0.2.2.dist-info/LICENSE.txt
aioethereum-0.2.2.dist-info/METADATA
aioethereum-0.2.2.dist-info/RECORD
aioethereum-0.2.2.dist-info/WHEEL
aioethereum-0.2.2.dist-info/metadata.json
aioethereum-0.2.2.dist-info/top_level.txt
