Metadata-Version: 2.0
Name: aioethereum
Version: 0.2.2
Summary: Ethereum RPC client library for Python asyncio (PEP 3156)
Home-page: https://github.com/DeV1doR/aioethereum
Author: Bogdan Kurinnyi
Author-email: bogdankurinniy.dev1@gmail.com
License: MIT
Platform: POSIX
Classifier: License :: OSI Approved :: MIT License
Classifier: Development Status :: 4 - Beta
Classifier: Programming Language :: Python
Classifier: Programming Language :: Python :: 3
Classifier: Programming Language :: Python :: 3.4
Classifier: Programming Language :: Python :: 3.5
Classifier: Programming Language :: Python :: 3.6
Classifier: Operating System :: POSIX
Classifier: Environment :: Web Environment
Classifier: Intended Audience :: Developers
Classifier: Topic :: Software Development
Classifier: Topic :: Software Development :: Libraries
Classifier: Framework :: AsyncIO
Requires-Dist: aiohttp (>=2.2.5)
Requires-Dist: async-timeout (>=1.4.0)
Requires-Dist: ujson
